autorag/__init__.py
autorag/core/__init__.py
autorag/core/credential.py
autorag/document_loaders/__init__.py
autorag/document_parsers/__init__.py
autorag/embedding/__init__.py
autorag/embedding/base.py
autorag/embedding/google.py
autorag/embedding/huggingface.py
autorag/embedding/modelhub.py
autorag/embedding/openai/__init__.py
autorag/embedding/openai/azure_openai.py
autorag/embedding/openai/base_openai.py
autorag/exceptions/__init__.py
autorag/exceptions/core/__init__.py
autorag/exceptions/core/credentials.py
autorag/exceptions/language_models.py
autorag/exceptions/vector_stores.py
autorag/language_models/__init__.py
autorag/language_models/anthropic.py
autorag/language_models/base.py
autorag/language_models/google.py
autorag/language_models/modelhub.py
autorag/language_models/ollama.py
autorag/language_models/openai/__init__.py
autorag/language_models/openai/azure_open_ai_with_proxy.py
autorag/language_models/openai/azure_openai.py
autorag/language_models/openai/base_openai.py
autorag/language_models/openai/rest_api_openai.py
autorag/memory/__init__.py
autorag/postprocessor/__init__.py
autorag/py.typed
autorag/reranking/__init__.py
autorag/reranking/base.py
autorag/reranking/colbert.py
autorag/reranking/cross_encoder.py
autorag/reranking/modelhub.py
autorag/storage/__init__.py
autorag/text_splitter/__init__.py
autorag/tools/__init__.py
autorag/tools/calling.py
autorag/types/__init__.py
autorag/types/language_models/__init__.py
autorag/types/language_models/generation.py
autorag/types/reranking/__init__.py
autorag/types/reranking/rerank.py
autorag/types/vector_stores/__init__.py
autorag/types/vector_stores/distance.py
autorag/types/vector_stores/search.py
autorag/utilities/__init__.py
autorag/utilities/concurrency.py
autorag/utilities/logger.py
autorag/vector_stores/__init__.py
autorag/vector_stores/azure_ai_search.py
autorag/vector_stores/base.py
autorag/vector_stores/mongodb_atlas.py
autorag/vector_stores/qdrant.py
autonomize_autorag-0.1.84.dist-info/METADATA
autonomize_autorag-0.1.84.dist-info/WHEEL
autonomize_autorag-0.1.84.dist-info/licenses/LICENSE
autonomize_autorag-0.1.84.dist-info/RECORD
