Metadata-Version: 2.4
Name: autonomize-autorag
Version: 0.1.84
Summary: AutoRAG is a flexible and scalable solution for building Retrieval-Augmented Generation (RAG) systems.
License: Proprietary
License-File: LICENSE
Author: Varun
Author-email: varun.prakash@autonomize.ai
Requires-Python: >=3.12,<3.15
Classifier: Development Status :: 3 - Alpha
Classifier: Intended Audience :: Developers
Classifier: License :: Other/Proprietary License
Classifier: Natural Language :: English
Classifier: Operating System :: OS Independent
Classifier: Programming Language :: Python :: 3
Classifier: Programming Language :: Python :: 3.12
Classifier: Programming Language :: Python :: 3.13
Classifier: Programming Language :: Python :: 3.14
Classifier: Topic :: Scientific/Engineering :: Artificial Intelligence
Classifier: Topic :: Software Development :: Libraries :: Application Frameworks
Classifier: Topic :: Software Development :: Libraries :: Python Modules
Classifier: Topic :: Text Processing
Classifier: Typing :: Typed
Provides-Extra: anthropic
Provides-Extra: azure-ai-search
Provides-Extra: google-genai
Provides-Extra: huggingface
Provides-Extra: modelhub
Provides-Extra: mongodb-atlas
Provides-Extra: openai
Provides-Extra: qdrant
Provides-Extra: vertex-ai-vector-search
Requires-Dist: aiohttp (>=3.10.11,<4.0.0)
Requires-Dist: anthropic (>=0.49.0,<0.50.0) ; extra == "anthropic"
Requires-Dist: anyio (>=4.4.0,<5.0.0)
Requires-Dist: autonomize-core (>=0.1.6,<0.2.0)
Requires-Dist: azure-identity (>=1.21.0,<2.0.0) ; extra == "azure-ai-search"
Requires-Dist: azure-search-documents (==11.4.0) ; extra == "azure-ai-search"
Requires-Dist: google-cloud-aiplatform (>=1.88.0,<2.0.0) ; extra == "vertex-ai-vector-search"
Requires-Dist: google-genai (==1.10.0) ; extra == "google-genai"
Requires-Dist: h11 (>=0.16.0,<0.17.0)
Requires-Dist: httpx (==0.28.1) ; extra == "modelhub"
Requires-Dist: jinja2 (>=3.1.5,<4.0.0)
Requires-Dist: motor (==3.6.0) ; extra == "mongodb-atlas"
Requires-Dist: openai (>=1.73.0,<2.0.0) ; extra == "openai"
Requires-Dist: pydantic (>=2.9.2,<3.0.0)
Requires-Dist: pymongo (==4.9) ; extra == "mongodb-atlas"
Requires-Dist: qdrant-client (==1.11.1) ; extra == "qdrant"
Requires-Dist: requests (>=2.32.4,<3.0.0)
Requires-Dist: sentence-transformers (>=3.0.1,<4.0.0) ; extra == "huggingface"
Requires-Dist: tenacity (>=9.1.2,<10.0.0)
Requires-Dist: tqdm (>=4.66.5,<5.0.0)
Requires-Dist: types-tqdm (>=4.66.0.20240417,<5.0.0.0)
Requires-Dist: urllib3 (>=2.5.0,<3.0.0)
Project-URL: Documentation, https://github.com/autonomize-ai/AutoRAG
Project-URL: Homepage, https://github.com/autonomize-ai/AutoRAG
Project-URL: Repository, https://github.com/autonomize-ai/AutoRAG
